{
  "servers": 4,
  "members": 1,
  "totalSongsPlayed": 464,
  "totalPlaytime": 236157470,
  "totalCommandsExecuted": 504,
  "botUptime": "0h 0m",
  "uptimeSeconds": 2083,
  "twentyFourSevenServers": 0,
  "errorCount": 4,
  "errorRate": 0.79,
  "recentlyPlayed": [
    {
      "title": "Maruvake Viduvake",
      "author": "DILIP DEVAGAN",
      "uri": "https://open.spotify.com/track/0m2jDS313PotphW7V1Xh8l",
      "requester": "744044949942829127",
      "timestamp": 1772039892236,
      "guildId": "1475911093330251990"
    },
    {
      "title": "Maruvake Viduvake",
      "author": "DILIP DEVAGAN",
      "uri": "https://open.spotify.com/track/0m2jDS313PotphW7V1Xh8l",
      "requester": "744044949942829127",
      "timestamp": 1772039873237,
      "guildId": "1475911093330251990"
    },
    {
      "title": "Maruvake Viduvake",
      "author": "DILIP DEVAGAN",
      "uri": "https://open.spotify.com/track/0m2jDS313PotphW7V1Xh8l",
      "requester": "744044949942829127",
      "timestamp": 1772039502616,
      "guildId": "1475911093330251990"
    },
    {
      "title": "Nuvvunte Naa Jathagaa",
      "author": "Sid Sriram",
      "uri": "https://www.youtube.com/watch?v=8BtSoNMdQqQ",
      "requester": "744044949942829127",
      "timestamp": 1772039013150,
      "guildId": "1475911093330251990"
    },
    {
      "title": "Nuvvunte Naa Jathagaa",
      "author": "Sid Sriram",
      "uri": "https://www.youtube.com/watch?v=8BtSoNMdQqQ",
      "requester": "744044949942829127",
      "timestamp": 1772038990634,
      "guildId": "1475911093330251990"
    },
    {
      "title": "Nuvvunte Naa Jathagaa",
      "author": "Sid Sriram",
      "uri": "https://www.youtube.com/watch?v=8BtSoNMdQqQ",
      "requester": "744044949942829127",
      "timestamp": 1772038447696,
      "guildId": "1475911093330251990"
    },
    {
      "title": "Nuvvunte Naa Jathagaa",
      "author": "Sid Sriram",
      "uri": "https://www.youtube.com/watch?v=8BtSoNMdQqQ",
      "requester": "744044949942829127",
      "timestamp": 1772038241251,
      "guildId": "1475911093330251990"
    },
    {
      "title": "KOTADATI RAVE SILAKAMMA",
      "author": "Dilip Devgan - Topic",
      "uri": "https://www.youtube.com/watch?v=GSX2MBj1DqE",
      "requester": "744044949942829127",
      "timestamp": 1772038034945,
      "guildId": "1475911093330251990"
    },
    {
      "title": "Maruvake Viduvake",
      "author": "DILIP DEVAGAN",
      "uri": "https://open.spotify.com/track/0m2jDS313PotphW7V1Xh8l",
      "requester": "744044949942829127",
      "timestamp": 1772037985367,
      "guildId": "1475911093330251990"
    },
    {
      "title": "Nuvvunte Naa Jathagaa",
      "author": "Sid Sriram",
      "uri": "https://www.youtube.com/watch?v=8BtSoNMdQqQ",
      "requester": "744044949942829127",
      "timestamp": 1772037964110,
      "guildId": "1475911093330251990"
    }
  ],
  "topGuilds": [
    {
      "guildId": "1475011449834176543",
      "songCount": 266,
      "guildName": "Bot setting"
    },
    {
      "guildId": "1475911093330251990",
      "songCount": 75,
      "guildName": "all bots !! 🔥"
    },
    {
      "guildId": "1469974428908654818",
      "songCount": 71,
      "guildName": "Unknown"
    },
    {
      "guildId": "1466778869834191026",
      "songCount": 52,
      "guildName": "Unknown"
    }
  ],
  "topArtists": [
    {
      "name": "Lil Skies",
      "count": 53
    },
    {
      "name": "Mohit Chauhan",
      "count": 32
    },
    {
      "name": "Devi Sri Prasad",
      "count": 30
    },
    {
      "name": "Shahil Hada",
      "count": 27
    },
    {
      "name": "Sid Sriram",
      "count": 19
    },
    {
      "name": "Chitra",
      "count": 17
    },
    {
      "name": "Feel The Music",
      "count": 15
    },
    {
      "name": "Nakash Aziz",
      "count": 13
    },
    {
      "name": "M.M. Sreelekha",
      "count": 12
    },
    {
      "name": "Jennifer Lopez - Topic",
      "count": 12
    }
  ],
  "updated": "2026-02-26T02:03:46.735Z"
}